{
  "price_targets": {
    "median": null,
    "mean": null,
    "high": null,
    "low": null,
    "analystCount": null,
    "asof": "2025-09-17T23:35:10Z"
  },
  "recommendations": {
    "strongBuy": 2,
    "buy": 10,
    "hold": 5,
    "sell": 0,
    "strongSell": 0,
    "asof": "2025-09-17T23:35:10Z"
  },
  "_history": {
    "rec_index": [
      {
        "ts": "2025-09-17T23:35:10Z",
        "value": 41.1764705882353
      }
    ],
    "pt_median": [
      {
        "ts": "2025-09-17T23:35:12Z",
        "value": 49.0
      }
    ]
  },
  "earnings": {
    "eps_surprise_avg": null,
    "rev_beat_rate": null,
    "asof": "2025-09-17T23:35:10Z"
  },
  "asof": "2025-09-17T23:35:10Z"
}