{
  "price_targets": {
    "median": null,
    "mean": null,
    "high": null,
    "low": null,
    "analystCount": null,
    "asof": "2025-09-18T00:42:10Z"
  },
  "recommendations": {
    "strongBuy": 10,
    "buy": 18,
    "hold": 8,
    "sell": 0,
    "strongSell": 0,
    "asof": "2025-09-18T00:42:10Z"
  },
  "_history": {
    "rec_index": [
      {
        "ts": "2025-09-18T00:42:10Z",
        "value": 52.77777777777778
      }
    ],
    "pt_median": [
      {
        "ts": "2025-09-18T00:42:13Z",
        "value": 128.0
      }
    ]
  },
  "earnings": {
    "eps_surprise_avg": null,
    "rev_beat_rate": null,
    "asof": "2025-09-18T00:42:10Z"
  },
  "asof": "2025-09-18T00:42:10Z"
}