{
  "price_targets": {
    "median": null,
    "mean": null,
    "high": null,
    "low": null,
    "analystCount": null,
    "asof": "2025-09-18T00:27:20Z"
  },
  "recommendations": {
    "strongBuy": 4,
    "buy": 6,
    "hold": 4,
    "sell": 0,
    "strongSell": 0,
    "asof": "2025-09-18T00:27:20Z"
  },
  "_history": {
    "rec_index": [
      {
        "ts": "2025-09-17T23:36:19Z",
        "value": 50.0
      },
      {
        "ts": "2025-09-18T00:27:20Z",
        "value": 50.0
      }
    ],
    "pt_median": [
      {
        "ts": "2025-09-17T23:36:21Z",
        "value": 85.0
      },
      {
        "ts": "2025-09-18T00:27:22Z",
        "value": 85.0
      }
    ]
  },
  "earnings": {
    "eps_surprise_avg": null,
    "rev_beat_rate": null,
    "asof": "2025-09-18T00:27:20Z"
  },
  "asof": "2025-09-18T00:27:20Z"
}